chatInsights/__init__.py
chatInsights/_custom_exceptions.py
chatInsights/_logger.py
chatInsights/main.py
chatInsights/utils.py
chatInsights-0.0.2.dist-info/LICENSE
chatInsights-0.0.2.dist-info/METADATA
chatInsights-0.0.2.dist-info/WHEEL
chatInsights-0.0.2.dist-info/top_level.txt
chatInsights-0.0.2.dist-info/RECORD
