Metadata-Version: 2.1
Name: chatInsights
Version: 0.0.2
Summary: whatsapp group chat analysis python package
Home-page: https://github.com/ronylpatil/chatInsights
Author: ronilpatil
Author-email: ronylpatil@gmail.com
License: MIT
Project-URL: Source, https://github.com/ronylpatil/chatInsights
Project-URL: Bug Tracker, https://github.com/ronylpatil/chatInsights/issues
Project-URL: Changelog, https://github.com/ronylpatil/chatInsights/releases
Keywords: chat analysis,statistical analysis,eda
Classifier: Development Status :: 4 - Beta
Classifier: License :: OSI Approved :: MIT License
Classifier: Operating System :: MacOS
Classifier: Operating System :: Microsoft :: Windows
Classifier: Operating System :: POSIX :: Linux
Classifier: Environment :: Console
Classifier: Natural Language :: English
Classifier: Intended Audience :: Developers
Classifier: Intended Audience :: Science/Research
Classifier: Programming Language :: Python :: 3.9
Classifier: Programming Language :: Python :: 3.10
Classifier: Programming Language :: Python :: 3.11
Classifier: Programming Language :: Python :: 3.12
Classifier: Topic :: Communications :: Chat
Classifier: Topic :: Scientific/Engineering :: Information Analysis
Classifier: Topic :: Scientific/Engineering :: Visualization
Requires-Python: >=3.9
License-File: LICENSE
Provides-Extra: testing
Requires-Dist: pytest >=8.2.2 ; extra == 'testing'
Requires-Dist: mypy >=1.10.0 ; extra == 'testing'
Requires-Dist: flake8 >=7.0.0 ; extra == 'testing'
Requires-Dist: tox >=4.15.1 ; extra == 'testing'
Requires-Dist: black >=24.4.2 ; extra == 'testing'
